parsethisio/__init__.py
parsethisio/exceptions.py
parsethisio/utils.py
parsethisio/content_parser/__init__.py
parsethisio/content_parser/archive_parser.py
parsethisio/content_parser/audio_parser.py
parsethisio/content_parser/base_parser.py
parsethisio/content_parser/data_parser.py
parsethisio/content_parser/image_parser.py
parsethisio/content_parser/office_parser.py
parsethisio/content_parser/pdf_parser.py
parsethisio/content_parser/text_parser.py
parsethisio/content_parser/helpers/__init__.py
parsethisio/content_parser/helpers/youtube_transcript_helper.py
parsethisio-0.2.3.dist-info/licenses/LICENSE
parsethisio-0.2.3.dist-info/METADATA
parsethisio-0.2.3.dist-info/WHEEL
parsethisio-0.2.3.dist-info/top_level.txt
parsethisio-0.2.3.dist-info/RECORD
