Metadata-Version: 2.4
Name: parsethisio
Version: 0.2.3
Summary: A Python library to extract text from various sources for LLM preprocessing.
Author-email: Jörn Depenbrock <joern@jdde.de>
License: GNU Affero General Public License v3.0
Keywords: text extraction,LLM,PDF,web,preprocessing
Classifier: Programming Language :: Python :: 3
Classifier: Operating System :: OS Independent
Requires-Python: <4.0,>=3.10
License-File: LICENSE
Requires-Dist: requests
Requires-Dist: PyPDF2
Requires-Dist: coverage
Requires-Dist: openai==1.70.0
Requires-Dist: filetype==1.2.0
Requires-Dist: scrapegraphai==1.46.0
Requires-Dist: youtube_transcript_api==0.6.3
Requires-Dist: loguru
Requires-Dist: gitingest==0.1.4
Requires-Dist: aiohttp
Requires-Dist: markitdown==0.0.2
Requires-Dist: beautifulsoup4
Provides-Extra: dev
Requires-Dist: coverage; extra == "dev"
Requires-Dist: coverage-badge; extra == "dev"
Requires-Dist: pytest; extra == "dev"
Dynamic: license-file
